sarcgraph/__init__.py
sarcgraph/sg.py
sarcgraph/sg_tools.py
sarcgraph-0.2.1.dist-info/LICENSE
sarcgraph-0.2.1.dist-info/METADATA
sarcgraph-0.2.1.dist-info/WHEEL
sarcgraph-0.2.1.dist-info/top_level.txt
sarcgraph-0.2.1.dist-info/RECORD
