Metadata-Version: 2.1
Name: sarcgraph
Version: 0.2.1
Summary: A software for sarcomere detection and tracking
Home-page: https://pypi.org/project/sarcgraph/
Author: Saeed Mohammadzadeh
Author-email: saeedmhz@bu.edu
Maintainer: [('Saeed Mohammadzadeh', 'saeedmhz@bu.edu'), ('Emma Lejeune', 'elejeune@bu.edu')]
License: MIT
Project-URL: Source, https://github.com/Sarc-Graph/sarcgraph
Project-URL: Documentation, https://sarc-graph.readthedocs.io/en/latest/
Classifier: License :: OSI Approved :: MIT License
Classifier: Programming Language :: Python :: 3
Classifier: Programming Language :: Python :: 3.10
License-File: LICENSE
Requires-Dist: matplotlib (==3.5.2)
Requires-Dist: networkx (==2.8.4)
Requires-Dist: numpy (==1.23.5)
Requires-Dist: pandas (==1.5.2)
Requires-Dist: scikit-image (==0.19.3)
Requires-Dist: scikit-learn (==1.2.1)
Requires-Dist: scipy (==1.10.0)
Requires-Dist: sk-video (==1.1.10)
Requires-Dist: trackpy (==0.6.1)
